airo_planner/__init__.py
airo_planner/exceptions.py
airo_planner/function_conversions.py
airo_planner/interfaces.py
airo_planner/joint_bounds.py
airo_planner/multiple_goal_planner.py
airo_planner/path_conversions.py
airo_planner/__pycache__/__init__.cpython-310.pyc
airo_planner/__pycache__/exceptions.cpython-310.pyc
airo_planner/__pycache__/function_conversions.cpython-310.pyc
airo_planner/__pycache__/interfaces.cpython-310.pyc
airo_planner/__pycache__/joint_bounds.cpython-310.pyc
airo_planner/__pycache__/multiple_goal_planner.cpython-310.pyc
airo_planner/__pycache__/path_conversions.cpython-310.pyc
airo_planner/curobo/rerun_visualizer.py
airo_planner/curobo/single_arm_curobo_planner.py
airo_planner/curobo/__pycache__/rerun_visualizer.cpython-310.pyc
airo_planner/curobo/__pycache__/robot.cpython-310.pyc
airo_planner/curobo/__pycache__/single_arm_curobo_planner.cpython-310.pyc
airo_planner/ompl/__init__.py
airo_planner/ompl/dual_arm_ompl_planner.py
airo_planner/ompl/mobile_platform_ompl_planner.py
airo_planner/ompl/single_arm_ompl_planner.py
airo_planner/ompl/utilities.py
airo_planner/ompl/__pycache__/__init__.cpython-310.pyc
airo_planner/ompl/__pycache__/dual_arm_ompl_planner.cpython-310.pyc
airo_planner/ompl/__pycache__/mobile_platform_ompl_planner.cpython-310.pyc
airo_planner/ompl/__pycache__/single_arm_ompl_planner.cpython-310.pyc
airo_planner/ompl/__pycache__/utilities.cpython-310.pyc
airo_planner/selection/goal_selection.py
airo_planner/selection/path_selection.py
airo_planner/selection/__pycache__/goal_selection.cpython-310.pyc
airo_planner/selection/__pycache__/path_selection.cpython-310.pyc
airo_planner-0.0.6.dist-info/licenses/LICENSE
test/ompl/single_arm/test_basic_planning.py
test/ompl/single_arm/test_exceptions.py
airo_planner-0.0.6.dist-info/METADATA
airo_planner-0.0.6.dist-info/WHEEL
airo_planner-0.0.6.dist-info/top_level.txt
airo_planner-0.0.6.dist-info/RECORD
