Metadata-Version: 2.4
Name: airo-planner
Version: 0.0.6
Summary: Motion planning for single and dual robot arms.
Author-email: Andreas Verleysen <andreas.verleysen@ugent.be>, Victor-Louis De Gusseme <victorlouisdg@gmail.com>, Mathieu De Coster <mathieu.decoster@ugent.be>
Project-URL: Homepage, https://github.com/airo-ugent/airo-planner
Project-URL: Issues, https://github.com/airo-ugent/airo-planner/issues
Classifier: Programming Language :: Python :: 3
Classifier: License :: OSI Approved :: MIT License
Classifier: Operating System :: OS Independent
Requires-Python: >=3.10
License-File: LICENSE
Requires-Dist: airo-drake>=0.0.8
Requires-Dist: airo-typing>=2025.11.0
Requires-Dist: loguru>=0.7.3
Requires-Dist: ompl>=1.7.0
Requires-Dist: yourdfpy>=0.0.58
Provides-Extra: rerun
Requires-Dist: rerun-sdk>=0.27.2; extra == "rerun"
Dynamic: license-file
